kedro_projetaai/__init__.py
kedro_projetaai/cli/__init__.py
kedro_projetaai/cli/cli.py
kedro_projetaai/cli/constants.py
kedro_projetaai/cli/local.py
kedro_projetaai/cli/model.py
kedro_projetaai/cli/new.py
kedro_projetaai/cli/pipeline.py
kedro_projetaai/cli/plugin.py
kedro_projetaai/cli/run.py
kedro_projetaai/cli/starter.py
kedro_projetaai/overrides.py
kedro_projetaai/packing/__init__.py
kedro_projetaai/packing/suggestions.py
kedro_projetaai/plugin.py
kedro_projetaai/serving/__init__.py
kedro_projetaai/serving/model.py
kedro_projetaai/starters.py
kedro_projetaai/utils/__init__.py
kedro_projetaai/utils/io.py
kedro_projetaai/utils/iterable.py
kedro_projetaai/utils/kedro.py
kedro_projetaai/utils/script.py
kedro_projetaai/utils/string.py
kedro_projetaai/utils/typing.py
kedro_projetaai-0.1.0b1.dist-info/entry_points.txt
kedro_projetaai-0.1.0b1.dist-info/WHEEL
kedro_projetaai-0.1.0b1.dist-info/METADATA
kedro_projetaai-0.1.0b1.dist-info/RECORD
